topsis/__init__.py
topsis/topsis.py
topsis_khushveer_102303327-0.0.2.dist-info/licenses/LICENSE
topsis_khushveer_102303327-0.0.2.dist-info/METADATA
topsis_khushveer_102303327-0.0.2.dist-info/WHEEL
topsis_khushveer_102303327-0.0.2.dist-info/entry_points.txt
topsis_khushveer_102303327-0.0.2.dist-info/top_level.txt
topsis_khushveer_102303327-0.0.2.dist-info/RECORD
