Metadata-Version: 2.4
Name: Topsis-Khushveer-102303327
Version: 0.0.2
Summary: TOPSIS implementation as a command line tool
Author: Khushveer Kaur
Author-email: kkaur3_be23@thapar.edu
Requires-Python: >=3.7
License-File: LICENSE
Requires-Dist: numpy
Requires-Dist: pandas
Dynamic: author
Dynamic: author-email
Dynamic: description
Dynamic: description-content-type
Dynamic: license-file
Dynamic: requires-dist
Dynamic: requires-python
Dynamic: summary
